webquiz_stress_test/__init__.py
webquiz_stress_test/binary_entry.py
webquiz_stress_test/build.py
webquiz_stress_test/cli.py
webquiz_stress_test/stress_test.py
webquiz_stress_test-0.1.2.dist-info/METADATA
webquiz_stress_test-0.1.2.dist-info/WHEEL
webquiz_stress_test-0.1.2.dist-info/entry_points.txt
webquiz_stress_test-0.1.2.dist-info/licenses/LICENSE
webquiz_stress_test-0.1.2.dist-info/RECORD
