Metadata-Version: 2.4
Name: webquiz-stress-test
Version: 0.1.2
Summary: Performance testing tool for WebQuiz servers - simulate concurrent users taking quizzes
License: MIT
License-File: LICENSE
Keywords: webquiz,stress-test,load-test,performance,testing,benchmark
Author: Oleksandr Liabakh
Author-email: oduvan@gmail.com
Requires-Python: >=3.9,<3.15
Classifier: Development Status :: 3 - Alpha
Classifier: Intended Audience :: Developers
Classifier: Intended Audience :: Education
Classifier: License :: OSI Approved :: MIT License
Classifier: Operating System :: OS Independent
Classifier: Programming Language :: Python :: 3
Classifier: Programming Language :: Python :: 3.9
Classifier: Programming Language :: Python :: 3.10
Classifier: Programming Language :: Python :: 3.11
Classifier: Programming Language :: Python :: 3.12
Classifier: Programming Language :: Python :: 3.13
Classifier: Programming Language :: Python :: 3.14
Classifier: Topic :: Software Development :: Testing
Classifier: Topic :: Software Development :: Testing :: Traffic Generation
Requires-Dist: aiohttp (>=3.12.13,<4.0.0)
Project-URL: Bug Tracker, https://github.com/oduvan/webquiz-stress-test/issues
Project-URL: Documentation, https://github.com/oduvan/webquiz-stress-test
Project-URL: Homepage, https://github.com/oduvan/webquiz-stress-test
Project-URL: Repository, https://github.com/oduvan/webquiz-stress-test
